{
    "display": {
        "icon": {
            "item": "minecraft:fishing_rod",
            "nbt": "{Damage:4,Unbreakable:1b,CustomModelData:60}"
        },
        "title": {
            "translate": "medabots_server:advancements.get_all_medabots.ka_o_lantern"
        },
        "description": {
            "translate": "medabots_server:advancements.get_all_medabots.ka_o_lantern.description"
        }
    },
    "parent": "medabots_server:get_all_medabots/wave_1/grade_kabuki",
    "criteria": {
        "head": {
            "trigger": "minecraft:inventory_changed",
            "conditions": {
                "items": [
                    {
                        "nbt": "{medabots_server:{stage_item:0b,id:\"medabots_server:ka_o_lantern_pan\"}}"
                    }
                ]
            }
        },
        "right_arm": {
            "trigger": "minecraft:inventory_changed",
            "conditions": {
                "items": [
                    {
                        "nbt": "{medabots_server:{stage_item:0b,id:\"medabots_server:ka_o_lantern_pun\"}}"
                    }
                ]
            }
        },
        "left_arm": {
            "trigger": "minecraft:inventory_changed",
            "conditions": {
                "items": [
                    {
                        "nbt": "{medabots_server:{stage_item:0b,id:\"medabots_server:ka_o_lantern_keen\"}}"
                    }
                ]
            }
        },
        "legs": {
            "trigger": "minecraft:inventory_changed",
            "conditions": {
                "items": [
                    {
                        "nbt": "{medabots_server:{stage_item:0b,id:\"medabots_server:ka_o_lantern_squash_basher\"}}"
                    }
                ]
            }
        }
    },
    "rewards": {
        "function": "medabots_server:advancements/get_all_medabots/wave_1/ka_o_lantern"
    }
}